pyqliksense/QlikApplication.py
pyqliksense/QlikSenseInstance.py
pyqliksense/QlikTask.py
pyqliksense/QlikUser.py
pyqliksense/__init__.py
pyqliksense/connections/QlikHubApi.py
pyqliksense/connections/QlikRepository.py
pyqliksense/connections/__init__.py
pyqliksense/connections/engine/QlikEngine.py
pyqliksense/connections/engine/QlikEngineMessages.py
pyqliksense/connections/engine/QlikEngineSession.py
pyqliksense/connections/engine/__init__.py
pyqliksense/objects/QlikHyperCube.py
pyqliksense/objects/QlikSheet.py
pyqliksense/objects/__init__.py
pyqliksense/objects/vizualizations/KPIObject.py
pyqliksense/objects/vizualizations/LineChartObject.py
pyqliksense/objects/vizualizations/QlikAppObject.py
pyqliksense/objects/vizualizations/__init__.py
pyqliksense/objects/vizualizations/definitions/__init__.py
pyqliksense/objects/vizualizations/definitions/kpi.py
pyqliksense/objects/vizualizations/definitions/linechart.py
pyqliksense/utils/__init__.py
pyqliksense/utils/functions.py
pyqliksense-0.0.8.dist-info/LICENSE
pyqliksense-0.0.8.dist-info/METADATA
pyqliksense-0.0.8.dist-info/WHEEL
pyqliksense-0.0.8.dist-info/top_level.txt
pyqliksense-0.0.8.dist-info/RECORD
